LICENSE
MANIFEST.in
README.rst
setup.py
wagtailmodeladmin/__init__.py
wagtailmodeladmin/forms.py
wagtailmodeladmin/helpers.py
wagtailmodeladmin/menus.py
wagtailmodeladmin/middleware.py
wagtailmodeladmin/options.py
wagtailmodeladmin/views.py
wagtailmodeladmin.egg-info/PKG-INFO
wagtailmodeladmin.egg-info/SOURCES.txt
wagtailmodeladmin.egg-info/dependency_links.txt
wagtailmodeladmin.egg-info/not-zip-safe
wagtailmodeladmin.egg-info/requires.txt
wagtailmodeladmin.egg-info/top_level.txt
wagtailmodeladmin/locale/nl/LC_MESSAGES/django.po
wagtailmodeladmin/recipes/__init__.py
wagtailmodeladmin/recipes/readonly/__init__.py
wagtailmodeladmin/recipes/readonly/helpers.py
wagtailmodeladmin/recipes/readonly/options.py
wagtailmodeladmin/static/wagtailmodeladmin/css/choose_parent_page.css
wagtailmodeladmin/static/wagtailmodeladmin/css/index.css
wagtailmodeladmin/templates/wagtailmodeladmin/choose_parent.html
wagtailmodeladmin/templates/wagtailmodeladmin/confirm_delete.html
wagtailmodeladmin/templates/wagtailmodeladmin/create.html
wagtailmodeladmin/templates/wagtailmodeladmin/edit.html
wagtailmodeladmin/templates/wagtailmodeladmin/index.html
wagtailmodeladmin/templates/wagtailmodeladmin/inspect.html
wagtailmodeladmin/templates/wagtailmodeladmin/includes/breadcrumb.html
wagtailmodeladmin/templates/wagtailmodeladmin/includes/button.html
wagtailmodeladmin/templates/wagtailmodeladmin/includes/filter.html
wagtailmodeladmin/templates/wagtailmodeladmin/includes/result_list.html
wagtailmodeladmin/templates/wagtailmodeladmin/includes/result_row.html
wagtailmodeladmin/templates/wagtailmodeladmin/includes/result_row_value.html
wagtailmodeladmin/templates/wagtailmodeladmin/includes/search_form.html
wagtailmodeladmin/templatetags/__init__.py
wagtailmodeladmin/templatetags/wagtailmodeladmin_tags.py