Metadata-Version: 1.1
Name: wagtailmodeladmin
Version: 2.5.7
Summary: Customisable 'django-admin' style listing pages for Wagtail
Home-page: https://github.com/rkhleics/wagtailmodeladmin
Author: Andy Babic
Author-email: ababic@rkh.co.uk
License: MIT
Download-URL: https://github.com/rkhleics/wagtailmodeladmin/tarball/0.1
Keywords: wagtail cms model utility
Platform: UNKNOWN
Classifier: Environment :: Web Environment
Classifier: Framework :: Django
Classifier: Intended Audience :: Developers
Classifier: Operating System :: OS Independent
Classifier: Programming Language :: Python
Classifier: Topic :: Internet :: WWW/HTTP
Classifier: Topic :: Internet :: WWW/HTTP :: Dynamic Content
